FILE_DESTROYER/__init__.py
FILE_DESTROYER/file_destroyer.py
file_destroyer-1.0.0.dist-info/LICENSE
file_destroyer-1.0.0.dist-info/METADATA
file_destroyer-1.0.0.dist-info/WHEEL
file_destroyer-1.0.0.dist-info/entry_points.txt
file_destroyer-1.0.0.dist-info/top_level.txt
file_destroyer-1.0.0.dist-info/RECORD
