Metadata-Version: 2.1
Name: file_destroyer
Version: 1.0.0
Summary: A GUI tool to permanently destroy files.
Home-page: https://github.com/Abhipratapsingh123/File_destroyer
Author: Abhi pratap singh
Author-email: Abhi.pratap9667@gmail.com
Classifier: Programming Language :: Python :: 3
Classifier: License :: OSI Approved :: MIT License
Classifier: Operating System :: OS Independent
Requires-Python: >=3.6
License-File: LICENSE
Requires-Dist: PyQt6
